xadnacos/__init__.py
xadnacos/cli.py
xadnacos/xadnacos.py
xadnacos-0.1.3.dist-info/AUTHORS.rst
xadnacos-0.1.3.dist-info/LICENSE
xadnacos-0.1.3.dist-info/METADATA
xadnacos-0.1.3.dist-info/WHEEL
xadnacos-0.1.3.dist-info/entry_points.txt
xadnacos-0.1.3.dist-info/top_level.txt
xadnacos-0.1.3.dist-info/RECORD
